pyxcp/__init__.py
pyxcp/aml/EtasCANMonitoring.a2l
pyxcp/aml/EtasCANMonitoring.aml
pyxcp/aml/ifdata_CAN.a2l
pyxcp/aml/ifdata_Eth.a2l
pyxcp/aml/ifdata_Flx.a2l
pyxcp/aml/ifdata_SxI.a2l
pyxcp/aml/ifdata_USB.a2l
pyxcp/aml/XCP_Common.aml
pyxcp/aml/XCPonCAN.aml
pyxcp/aml/XCPonEth.aml
pyxcp/aml/XCPonFlx.aml
pyxcp/aml/XCPonSxI.aml
pyxcp/aml/XCPonUSB.aml
pyxcp/asam/__init__.py
pyxcp/asam/types.py
pyxcp/asamkeydll.c
pyxcp/asamkeydll.exe
pyxcp/asamkeydll.sh
pyxcp/checksum.py
pyxcp/cmdline.py
pyxcp/config/__init__.py
pyxcp/config/legacy.py
pyxcp/constants.py
pyxcp/cpp_ext/__init__.py
pyxcp/cpp_ext/aligned_buffer.hpp
pyxcp/cpp_ext/bin.hpp
pyxcp/cpp_ext/blockmem.hpp
pyxcp/cpp_ext/cpp_ext.cp310-win_arm64.pyd
pyxcp/cpp_ext/cpp_ext.cp311-win_arm64.pyd
pyxcp/cpp_ext/cpp_ext.cp312-win_arm64.pyd
pyxcp/cpp_ext/cpp_ext.cp313-win_arm64.pyd
pyxcp/cpp_ext/cpp_ext.cp314-win_arm64.pyd
pyxcp/cpp_ext/daqlist.hpp
pyxcp/cpp_ext/event.hpp
pyxcp/cpp_ext/extension_wrapper.cpp
pyxcp/cpp_ext/framing.hpp
pyxcp/cpp_ext/helper.hpp
pyxcp/cpp_ext/mcobject.hpp
pyxcp/cpp_ext/sxi_framing.hpp
pyxcp/cpp_ext/tsqueue.hpp
pyxcp/daq_stim/__init__.py
pyxcp/daq_stim/optimize/__init__.py
pyxcp/daq_stim/optimize/binpacking.py
pyxcp/daq_stim/scheduler.cpp
pyxcp/daq_stim/scheduler.hpp
pyxcp/daq_stim/stim.cp310-win_arm64.pyd
pyxcp/daq_stim/stim.cp311-win_arm64.pyd
pyxcp/daq_stim/stim.cp312-win_arm64.pyd
pyxcp/daq_stim/stim.cp313-win_arm64.pyd
pyxcp/daq_stim/stim.cp314-win_arm64.pyd
pyxcp/daq_stim/stim.cpp
pyxcp/daq_stim/stim.hpp
pyxcp/daq_stim/stim_wrapper.cpp
pyxcp/dllif.py
pyxcp/errormatrix.py
pyxcp/examples/conf_can.toml
pyxcp/examples/conf_can_user.toml
pyxcp/examples/conf_can_vector.json
pyxcp/examples/conf_can_vector.toml
pyxcp/examples/conf_eth.toml
pyxcp/examples/conf_nixnet.json
pyxcp/examples/conf_socket_can.toml
pyxcp/examples/run_daq.py
pyxcp/examples/xcp_policy.py
pyxcp/examples/xcp_read_benchmark.py
pyxcp/examples/xcp_skel.py
pyxcp/examples/xcp_unlock.py
pyxcp/examples/xcp_user_supplied_driver.py
pyxcp-0.25.10.dist-info/entry_points.txt
pyxcp-0.25.10.dist-info/licenses/LICENSE
pyxcp-0.25.10.dist-info/METADATA
pyxcp-0.25.10.dist-info/WHEEL
pyxcp-0.25.10.dist-info/RECORD
