Metadata-Version: 2.4
Name: pyxcp
Version: 0.25.10
Summary: Universal Calibration Protocol for Python
License: LGPLv3
License-File: LICENSE
Keywords: automotive,ecu,xcp,asam,autosar
Author: Christoph Schueler
Author-email: cpu.gems@googlemail.com
Requires-Python: >=3.10,<4.0
Classifier: Development Status :: 5 - Production/Stable
Classifier: Intended Audience :: Developers
Classifier: License :: OSI Approved :: GNU Lesser General Public License v3 or later (LGPLv3+)
Classifier: License :: Other/Proprietary License
Classifier: Programming Language :: Python :: 3
Classifier: Programming Language :: Python :: 3.10
Classifier: Programming Language :: Python :: 3.11
Classifier: Programming Language :: Python :: 3.12
Classifier: Programming Language :: Python :: 3.13
Classifier: Programming Language :: Python :: 3.14
Classifier: Topic :: Scientific/Engineering
Classifier: Topic :: Software Development
Requires-Dist: bandit (>=1.7.8,<2.0.0)
Requires-Dist: chardet (>=5.2.0,<6.0.0)
Requires-Dist: construct (>=2.10.68,<3.0.0)
Requires-Dist: line-profiler-pycharm (>=1.1.0,<2.0.0)
Requires-Dist: mako (>=1.2.4,<2.0.0)
Requires-Dist: pydantic (>=2.5,<3)
Requires-Dist: pyserial (>=3.5,<4.0)
Requires-Dist: python-can (>=4.2.2,<5.0.0)
Requires-Dist: pytz (>=2025.2,<2026.0)
Requires-Dist: pyusb (>=1.2.1,<2.0.0)
Requires-Dist: rich (>=14.0.0,<15.0.0)
Requires-Dist: toml (>=0.10.2,<0.11.0)
Requires-Dist: tomlkit (>=0.13.3,<0.14.0)
Requires-Dist: traitlets (<=5.11.2)
Requires-Dist: uptime (>=3.0.1,<4.0.0)
Project-URL: Homepage, https://github.com/christoph2/pyxcp
